yescrypt.cp39-win32.pyd
yescrypt_koto-1.2.dist-info/METADATA
yescrypt_koto-1.2.dist-info/WHEEL
yescrypt_koto-1.2.dist-info/top_level.txt
yescrypt_koto-1.2.dist-info/RECORD
