Metadata-Version: 2.1
Name: yescrypt-koto
Version: 1.2
Summary: Bindings for yescrypt proof of work for Koto
Home-page: https://github.com/wo01/yescrypt_python/
Author: wo
Author-email: wo@kotocoin.info
License: UNKNOWN
Platform: UNKNOWN
